iotkaran/Client.py
iotkaran/__init__.py
iotkaran-0.0.2.dist-info/LICENSE
iotkaran-0.0.2.dist-info/METADATA
iotkaran-0.0.2.dist-info/WHEEL
iotkaran-0.0.2.dist-info/top_level.txt
iotkaran-0.0.2.dist-info/RECORD
